{
  "d": "2025-09-16",
  "ts": "LOCAL MOVE ",
  "pt": [
    "Others"
  ],
  "lastUpdatedBy": "ABDUL HADI ",
  "pc": "",
  "status": "pending",
  "mawb": "",
  "cl": [
    "Local Move"
  ],
  "createdAt": "2025-09-16T13:45:39.000Z",
  "cn": "",
  "totalSelling": 180,
  "bd": "",
  "po": "",
  "re": "",
  "tn": "",
  "vn": "",
  "pb": "ABDUL HADI ",
  "gw": "",
  "fv": "",
  "jfn": "LMK/00118/09/2025",
  "sm": "DINESH",
  "vw": "",
  "hawb": "",
  "updatedAt": "2025-09-16T13:45:39.000Z",
  "co": "MR. MISHARI AL ZAMEL",
  "dsc": "LOCAL MOVE ",
  "or": "EGAILA",
  "in": "",
  "ch": [
    {
      "c": "0",
      "n": "",
      "l": "LOCAL MOVE FROM EGAILA TO ABU HASSANIYA",
      "s": "180"
    }
  ],
  "totalCost": 0,
  "sh": "MR. MISHARI AL ZAMEL",
  "totalProfit": 180,
  "de": "ABU HASSANIYA",
  "createdBy": "ABDUL HADI ",
  "ca": ""
}